cli/__init__.py
cli/catren_cli.py
cli/render_cli.py
cli/rmdawn_cli.py
cli/rmdtor_cli.py
cli/rmdusk_cli.py
cli/rtormd_cli.py
rmdawn/__init__.py
rmdawn/catren.py
rmdawn/extract.py
rmdawn/render.py
rmdawn/rmdawn.py
rmdawn/rmdtor.py
rmdawn/rmdusk.py
rmdawn/rtormd.py
rmdawn-0.1.2.dist-info/AUTHORS.rst
rmdawn-0.1.2.dist-info/LICENSE
rmdawn-0.1.2.dist-info/METADATA
rmdawn-0.1.2.dist-info/WHEEL
rmdawn-0.1.2.dist-info/entry_points.txt
rmdawn-0.1.2.dist-info/top_level.txt
rmdawn-0.1.2.dist-info/RECORD
