Metadata-Version: 2.1
Name: rmdawn
Version: 0.1.2
Summary: Construct, deconstruct, and convert R markdown files.
Home-page: https://github.com/marskar/rmdawn
Author: Martin Skarzynski
Author-email: marskar@gmail.com
License: MIT license
Keywords: rmdawn
Platform: UNKNOWN
Classifier: Development Status :: 4 - Beta
Classifier: Intended Audience :: Developers
Classifier: License :: OSI Approved :: MIT License
Classifier: Natural Language :: English
Classifier: Programming Language :: Python :: 3.6
Classifier: Programming Language :: Python :: 3.7
Requires-Dist: Click (>=6.0)
Requires-Dist: rpy2
